simplipy_python/__init__.py
tests/__init__.py
tests/test_simplipy_python.py
simplipy_python-0.1.7.dist-info/LICENSE
simplipy_python-0.1.7.dist-info/METADATA
simplipy_python-0.1.7.dist-info/WHEEL
simplipy_python-0.1.7.dist-info/top_level.txt
simplipy_python-0.1.7.dist-info/RECORD
