Metadata-Version: 2.1
Name: simplipy-python
Version: 0.1.7
Summary: Create simple commands.
Home-page: https://replit.com/@AutumnApple/SimpleCommands#simplipy-python/
Author: Vermin1ty
Author-email: Vermin1ty@outlook.com
License: UNKNOWN
Platform: UNKNOWN
Classifier: Programming Language :: Python :: 3
Classifier: License :: OSI Approved :: MIT License
Classifier: Operating System :: OS Independent
Requires-Python: >=3.6
Requires-Dist: argparse
